__init__.py
enrichment_tools.py
enrichment_tools_data/__init__.py
enrichment_tools_data/enrichment.yaml
enrichment_tools-0.2.3.dist-info/METADATA
enrichment_tools-0.2.3.dist-info/WHEEL
enrichment_tools-0.2.3.dist-info/entry_points.txt
enrichment_tools-0.2.3.dist-info/top_level.txt
enrichment_tools-0.2.3.dist-info/RECORD
