Metadata-Version: 2.4
Name: enrichment_tools
Version: 0.2.3
Summary: MCP Server for catering to Enrichment APIs of Apollo.io
Author-email: Kavya-24 <kavya.goyal@apollo.io>
License: MIT
Classifier: Programming Language :: Python :: 3
Classifier: License :: OSI Approved :: MIT License
Classifier: Operating System :: OS Independent
Requires-Python: >=3.9
Requires-Dist: fastmcp==2.5.2
Requires-Dist: PyYAML==6.0.2
Requires-Dist: mcp>=1.2.0
Requires-Dist: requests
Requires-Dist: httpx
Requires-Dist: beautifulsoup4
Requires-Dist: pyyaml
